authit/__init__.py
authit-0.0.7.dist-info/METADATA
authit-0.0.7.dist-info/WHEEL
authit-0.0.7.dist-info/top_level.txt
authit-0.0.7.dist-info/RECORD
