Metadata-Version: 2.1
Name: authit
Version: 0.0.7
Summary: An identity platform
Home-page: https://github.com/muthugit/authit
Author: Muthu
Author-email: contact@muthupandian.in
Requires-Dist: bcrypt
